residPCA/__init__.py
residPCA/residPCA.py
residPCA-1.0.0.dist-info/METADATA
residPCA-1.0.0.dist-info/WHEEL
residPCA-1.0.0.dist-info/entry_points.txt
residPCA-1.0.0.dist-info/top_level.txt
residPCA-1.0.0.dist-info/RECORD
