Metadata-Version: 2.1
Name: residPCA
Version: 1.0.0
Summary: ResidPCA Toolkit
Home-page: https://github.com/carversh/residPCA
Author: Shaye Carver
Author-email: scarver@g.harvard.edu
Project-URL: Bug Tracker, https://github.com/carversh/residPCA/issues
Classifier: Programming Language :: Python :: 3
Classifier: License :: OSI Approved :: MIT License
Classifier: Operating System :: OS Independent
